odoo/addons/stock_barcodes/README.rst
odoo/addons/stock_barcodes/__init__.py
odoo/addons/stock_barcodes/__manifest__.py
odoo/addons/stock_barcodes/hooks.py
odoo/addons/stock_barcodes/data/stock_barcodes_action.xml
odoo/addons/stock_barcodes/data/stock_barcodes_option.xml
odoo/addons/stock_barcodes/i18n/es.po
odoo/addons/stock_barcodes/i18n/stock_barcodes.pot
odoo/addons/stock_barcodes/models/__init__.py
odoo/addons/stock_barcodes/models/stock_barcodes_action.py
odoo/addons/stock_barcodes/models/stock_barcodes_option.py
odoo/addons/stock_barcodes/models/stock_barcodes_read_log.py
odoo/addons/stock_barcodes/models/stock_inventory.py
odoo/addons/stock_barcodes/models/stock_move_line.py
odoo/addons/stock_barcodes/models/stock_picking.py
odoo/addons/stock_barcodes/models/stock_picking_type.py
odoo/addons/stock_barcodes/models/stock_production_lot.py
odoo/addons/stock_barcodes/readme/CONTRIBUTORS.rst
odoo/addons/stock_barcodes/readme/DESCRIPTION.rst
odoo/addons/stock_barcodes/readme/HISTORY.rst
odoo/addons/stock_barcodes/readme/ROADMAP.rst
odoo/addons/stock_barcodes/readme/USAGE.rst
odoo/addons/stock_barcodes/security/ir.model.access.csv
odoo/addons/stock_barcodes/static/description/icon.png
odoo/addons/stock_barcodes/static/description/icon.svg
odoo/addons/stock_barcodes/static/description/index.html
odoo/addons/stock_barcodes/static/src/css/stock.css
odoo/addons/stock_barcodes/static/src/css/stock.scss
odoo/addons/stock_barcodes/static/src/img/scan.png
odoo/addons/stock_barcodes/static/src/js/barcodes_models_mixin.js
odoo/addons/stock_barcodes/static/src/js/basic_controller.js
odoo/addons/stock_barcodes/static/src/js/basic_fields.js
odoo/addons/stock_barcodes/static/src/js/form_view.js
odoo/addons/stock_barcodes/static/src/js/kanban_renderer.js
odoo/addons/stock_barcodes/static/src/js/numeric_step.js
odoo/addons/stock_barcodes/static/src/sounds/bell.wav
odoo/addons/stock_barcodes/static/src/sounds/error.wav
odoo/addons/stock_barcodes/tests/__init__.py
odoo13_addon_stock_barcodes-13.0.2.3.4.dist-info/METADATA
odoo13_addon_stock_barcodes-13.0.2.3.4.dist-info/WHEEL
odoo13_addon_stock_barcodes-13.0.2.3.4.dist-info/top_level.txt
odoo13_addon_stock_barcodes-13.0.2.3.4.dist-info/RECORD
