Metadata-Version: 2.1
Name: odoo13-addon-stock-barcodes
Version: 13.0.2.3.4
Summary: It provides read barcode on stock operations.
Home-page: https://github.com/OCA/stock-logistics-barcode
Author: Tecnativa, Odoo Community Association (OCA)
Author-email: support@odoo-community.org
License: AGPL-3
Platform: UNKNOWN
Classifier: Programming Language :: Python
Classifier: Framework :: Odoo
Classifier: Framework :: Odoo :: 13.0
Classifier: License :: OSI Approved :: GNU Affero General Public License v3
Requires-Python: >=3.5
Requires-Dist: odoo13-addon-web-widget-numeric-step
Requires-Dist: odoo (<13.1dev,>=13.0a)
